sfta/__init__.py
sfta/_version.py
sfta/cli.py
sfta/core.py
sfta/utilities.py
sfta-0.9.1.dist-info/entry_points.txt
sfta-0.9.1.dist-info/WHEEL
sfta-0.9.1.dist-info/METADATA
sfta-0.9.1.dist-info/RECORD
