Metadata-Version: 2.3
Name: sfta
Version: 0.9.1
Summary: Slow Fault Tree Analyser (SFTA)
Keywords: fault tree,minimal cutsets
Author-email: Conway <pypi.sheep257@passmail.net>
Requires-Python: >=3.11
Classifier: Programming Language :: Python :: 3
Classifier: Programming Language :: Python :: 3.11
Classifier: Programming Language :: Python :: 3.12
Classifier: License :: OSI Approved :: GNU General Public License v3 (GPLv3)
Classifier: Operating System :: OS Independent
Project-URL: changelog, https://github.com/yawnoc/sfta/blob/master/CHANGELOG.md
Project-URL: issues, https://github.com/yawnoc/sfta/issues
Project-URL: repository, https://github.com/yawnoc/sfta
